{
  "entity.capybara.ambient": {
    "sounds": [
      "mobcatalog:entity/capybara/ambient1",
      "mobcatalog:entity/capybara/ambient2",
      "mobcatalog:entity/capybara/ambient3",
      "mobcatalog:entity/capybara/ambient4"
    ],
    "subtitle": "subtitles.mobcatalog.entity.capybara.ambient"
  },
  "entity.capybara.death": {
    "sounds": [
      "mobcatalog:entity/capybara/death"
    ],
    "subtitle": "subtitles.mobcatalog.entity.capybara.death"
  },
  "entity.capybara.eat": {
    "sounds": [
      "entity/horse/eat1",
      "entity/horse/eat2",
      "entity/horse/eat3",
      "entity/horse/eat4",
      "entity/horse/eat5"
    ],
    "subtitle": "subtitles.mobcatalog.entity.capybara.eat"
  },
  "entity.capybara.hurt": {
    "sounds": [
      "mobcatalog:entity/capybara/ambient1",
      "mobcatalog:entity/capybara/ambient2",
      "mobcatalog:entity/capybara/ambient3",
      "mobcatalog:entity/capybara/ambient4"
    ],
    "subtitle": "subtitles.mobcatalog.entity.capybara.hurt"
  },
  "entity.capybara.step": {
    "sounds": [
      "mobcatalog:entity/capybara/step"
    ],
    "subtitle": "subtitles.mobcatalog.entity.capybara.step"
  },
  "entity.crab.death": {
    "sounds": [
      "mobcatalog:entity/crab/death"
    ],
    "subtitle": "subtitles.mobcatalog.entity.crab.death"
  },
  "entity.crab.eat": {
    "sounds": [
      "mobcatalog:entity/crab/eat1",
      "mobcatalog:entity/crab/eat2"
    ],
    "subtitle": "subtitles.mobcatalog.entity.crab.eat"
  },
  "entity.crab.hurt": {
    "sounds": [
      "mobcatalog:entity/crab/hurt1",
      "mobcatalog:entity/crab/hurt2"
    ],
    "subtitle": "subtitles.mobcatalog.entity.crab.hurt"
  },
  "entity.crab.step": {
    "sounds": [
      "mobcatalog:entity/crab/step1",
      "mobcatalog:entity/crab/step2"
    ],
    "subtitle": "subtitles.mobcatalog.entity.crab.step"
  },
  "entity.penguin.ambient": {
    "sounds": [
      "mobcatalog:entity/penguin/ambient1",
      "mobcatalog:entity/penguin/ambient2",
      "mobcatalog:entity/penguin/ambient3",
      "mobcatalog:entity/penguin/ambient4"
    ],
    "subtitle": "subtitles.mobcatalog.entity.penguin.ambient"
  },
  "entity.penguin.death": {
    "sounds": [
      "mobcatalog:entity/penguin/death"
    ],
    "subtitle": "subtitles.mobcatalog.entity.penguin.death"
  },
  "entity.penguin.eat": {
    "sounds": [
      "mob/parrot/eat1",
      "mob/parrot/eat2",
      "mob/parrot/eat3"
    ],
    "subtitle": "subtitles.mobcatalog.entity.penguin.eat"
  },
  "entity.penguin.hurt": {
    "sounds": [
      "mobcatalog:entity/penguin/ambient1",
      "mobcatalog:entity/penguin/ambient2",
      "mobcatalog:entity/penguin/ambient3",
      "mobcatalog:entity/penguin/ambient4"
    ],
    "subtitle": "subtitles.mobcatalog.entity.penguin.hurt"
  },
  "entity.penguin.step": {
    "sounds": [
      "mobcatalog:entity/penguin/step"
    ],
    "subtitle": "subtitles.mobcatalog.entity.penguin.step"
  }
}